functionfaker
