Metadata-Version: 2.1
Name: functionfaker
Version: 0.1.4
Summary: Function Faker
Home-page: https://github.com/wsijp/functionfaker
Author: Will Sijp
Author-email: wim.sijp@gmail.com
License: UNKNOWN
Platform: UNKNOWN
Classifier: Programming Language :: Python :: 3
Classifier: License :: OSI Approved :: MIT License
Classifier: Operating System :: OS Independent
